{
  "offer_id": "ea492878",
  "created_at": "2026-06-26T14:55:23.073397",
  "status": "NEW",
  "raw": {
    "sender_id": 725768848,
    "sender_username": "tursunovaaa1",
    "chat_username": "mari_vakansii",
    "msg_id": 5784009,
    "msg_url": "https://t.me/mari_vakansii/5784009",
    "contact_url": "https://t.me/tursunovaaa1"
  },
  "raw_text": "#ищу #менеджер #переписки \n\nИщу человека, который проживает не в РФ, для работы в LinkedIn.\n\nЗадача — вести переписки с предпринимателями и экспертами и записывать их на консультации. Работа удалённая, всему обучим, опыт не обязателен.\n\nВажно: для работы потребуется аккаунт LinkedIn, который проходит верификацию. Поэтому рассматриваем кандидатов, которые проживают за пределами РФ и имеют документы, выданные не РФ. Это связано исключительно с требованиями платформы.\n\nЕсли вам интересно, напишите мне в личные сообщения немного о себе, страну проживания и возраст \n\n@tursunovaaa1",
  "display": {
    "chat_name": "Мари про вакансии — инфобизнес",
    "sender_name": "Amina",
    "date": "26.06 14:15",
    "keywords": [
      "#ищу"
    ],
    "ai_score": null,
    "score": null,
    "preview": "#ищу #менеджер #переписки \n\nИщу человека, который проживает не в РФ, для работы в LinkedIn.\n\nЗадача — вести переписки с предпринимателями и экспертами и записывать их на консультации. Работа удалённая, всему обучим, опыт не обязателен.\n\nВажно: для работы потребуется аккаунт LinkedIn, который проходит верификацию. Поэтому рассматриваем кандидатов, к..."
  },
  "deal_id": null
}